LICENSE
MANIFEST.in
README.md
setup.cfg
setup.py
swm/__init__.py
swm/events.py
swm/monitors.py
swm/servers.py
swm/tasks.py
swm/workers.py
swm.egg-info/PKG-INFO
swm.egg-info/SOURCES.txt
swm.egg-info/dependency_links.txt
swm.egg-info/requires.txt
swm.egg-info/top_level.txt
swm/population/__init__.py
swm/population/controls/__init__.py
swm/population/controls/on_demand.py
swm/population/controls/static.py
swm/population/spawners/__init__.py
swm/population/spawners/aws.py
swm/population/spawners/local.py
swm/population/spawners/static.py